qiskit_braket_provider/__init__.py
qiskit_braket_provider/exception.py
qiskit_braket_provider/version.py
qiskit_braket_provider/providers/__init__.py
qiskit_braket_provider/providers/adapter.py
qiskit_braket_provider/providers/braket_backend.py
qiskit_braket_provider/providers/braket_estimator.py
qiskit_braket_provider/providers/braket_instructions.py
qiskit_braket_provider/providers/braket_job.py
qiskit_braket_provider/providers/braket_primitive_task.py
qiskit_braket_provider/providers/braket_provider.py
qiskit_braket_provider/providers/braket_quantum_task.py
qiskit_braket_provider/providers/braket_sampler.py
qiskit_braket_provider-0.11.0.dist-info/licenses/LICENSE.txt
tests/__init__.py
tests/providers/__init__.py
tests/providers/mocks.py
tests/providers/test_adapter.py
tests/providers/test_braket_backend.py
tests/providers/test_braket_estimator.py
tests/providers/test_braket_instructions.py
tests/providers/test_braket_job.py
tests/providers/test_braket_primitive_task.py
tests/providers/test_braket_provider.py
tests/providers/test_braket_quantum_task.py
tests/providers/test_braket_sampler.py
qiskit_braket_provider-0.11.0.dist-info/METADATA
qiskit_braket_provider-0.11.0.dist-info/WHEEL
qiskit_braket_provider-0.11.0.dist-info/top_level.txt
qiskit_braket_provider-0.11.0.dist-info/RECORD
