Metadata-Version: 2.4
Name: qiskit_braket_provider
Version: 0.11.0
Summary: Qiskit-Braket provider to execute Qiskit programs on devices via Amazon Braket.
Keywords: qiskit braket sdk quantum
Classifier: Intended Audience :: Developers
Classifier: Intended Audience :: Science/Research
Classifier: License :: OSI Approved :: Apache Software License
Classifier: Natural Language :: English
Classifier: Operating System :: MacOS
Classifier: Operating System :: POSIX :: Linux
Classifier: Operating System :: Microsoft :: Windows
Classifier: Programming Language :: Python :: 3.11
Classifier: Programming Language :: Python :: 3.12
Classifier: Programming Language :: Python :: 3.13
Classifier: Topic :: Scientific/Engineering :: Physics
Requires-Python: >=3.11
License-File: LICENSE.txt
Requires-Dist: certifi>=2021.5.30
Requires-Dist: qiskit>=0.34.2
Requires-Dist: qiskit-ionq>=0.5.2
Requires-Dist: amazon-braket-sdk>=1.99.0
Requires-Dist: setuptools>=40.1.0
Requires-Dist: numpy>=1.3
Dynamic: classifier
Dynamic: description
Dynamic: description-content-type
Dynamic: keywords
Dynamic: license-file
Dynamic: requires-dist
Dynamic: requires-python
Dynamic: summary
